package/__init__.py
package/example.py
onessds-1.1.dist-info/LICENSE
onessds-1.1.dist-info/METADATA
onessds-1.1.dist-info/WHEEL
onessds-1.1.dist-info/top_level.txt
onessds-1.1.dist-info/RECORD
