Metadata-Version: 2.1
Name: onessds
Version: 1.1
Summary: BEST
Home-page: https://pypi.org/krest_null_best
Author: Python_Palma
Author-email: admin@gmail.com
Project-URL: Documentation, https://pypi.org/
Keywords: Snake,python
Classifier: Programming Language :: Python :: 3.11
Classifier: License :: OSI Approved :: MIT License
Classifier: Operating System :: OS Independent
Requires-Python: >=3.5
License-File: LICENSE
Requires-Dist: requests >=2.25.1
